{
  "simulation": {
    "initialPopulation": 100,
    "cyclesPerSecond": 10,
    "maxPopulation": 1000,
    "initialMode": "randomized"
  },
  "resources": {
    "maxTotalResources": 1000,
    "replenishmentRate": 1000,
    "defaultConsumptionRate": 3,
    "consumptionCanMutate": true,
    "utilizationCanMutate": true,
    "ageConsumptionConstant": 300
  },
  "genetics": {
    "numberOfAttributes": 8,
    "attributeNames": [
      "replicationRate",
      "attractiveness",
      "strength",
      "mutationChance",
      "intelligence",
      "resourceEfficiency",
      "consumptionRate",
      "utilizationFactor"
    ],
    "properties": {
      "replicationRate": {
        "min": 0,
        "max": 1,
        "default": 0.5
      },
      "attractiveness": {
        "min": 0,
        "max": 1,
        "default": 0.5
      },
      "strength": {
        "min": 0,
        "max": 1,
        "default": 0.5
      },
      "mutationChance": {
        "min": 0,
        "max": 1,
        "default": 0.1
      },
      "intelligence": {
        "min": 0,
        "max": 1,
        "default": 0.5
      },
      "resourceEfficiency": {
        "min": 0,
        "max": 1,
        "default": 0.5
      },
      "consumptionRate": {
        "min": 1,
        "max": 10,
        "default": 3
      },
      "utilizationFactor": {
        "min": 0.1,
        "max": 1.0,
        "default": 0.5
      }
    },
    "mutationStrength": 0.05,
    "inheritanceVariation": 0.05
  },
  "variants": {
    "groupingPrecision": 2,
    "useValueBasedId": true
  },
  "lifespan": {
    "baseLifespan": 100,
    "lifespanVariation": 20
  },
  "reproduction": {
    "spawnRandomness": 0.2,
    "attractivenessWeight": 0.7
  },
  "survival": {
    "threshold": 0.3,
    "strengthWeight": 0.6,
    "intelligenceWeight": 0.4,
    "randomFactor": 0.1
  },
  "interactions": {
    "attractivenessFromStrength": 0.4,
    "attractivenessFromIntelligence": 0.3,
    "replicationPenaltyThreshold": 0.3,
    "mutationBonusThreshold": 0.7
  },
  "mutation": {
    "perPropertyProbability": 0.01,
    "mutationStrength": 0.05,
    "independentMutation": true
  }
}
